Metadata-Version: 1.0
Name: shmlast
Version: 1.6
Summary: An improved implementation of Conditional Reciprocal Best Hits with LAST and Python.
Home-page: https://github.com/camillescott/shmlast
Author: Camille Scott
Author-email: camille.scott.w@gmail.com
License: BSD
Platform: UNKNOWN
